MANIFEST.in
setup.py
src/__init__.py
src/gen/__init__.py
src/gen/twitter/__init__.py
src/gen/twitter/finagle/__init__.py
src/gen/twitter/finagle/thrift/__init__.py
src/gen/twitter/finagle/thrift/constants.py
src/gen/twitter/finagle/thrift/ttypes.py
src/twitter.common.finagle_thrift.egg-info/PKG-INFO
src/twitter.common.finagle_thrift.egg-info/SOURCES.txt
src/twitter.common.finagle_thrift.egg-info/dependency_links.txt
src/twitter.common.finagle_thrift.egg-info/namespace_packages.txt
src/twitter.common.finagle_thrift.egg-info/top_level.txt
src/twitter.common.finagle_thrift.egg-info/zip-safe